projects/adder_subtractor_3bit/rtl/full_adder.v
`timescale 1ns / 1ps
module full_adder (
    input  a,
    b,
    c_in,
    output c_out,
    sum
);
  assign sum   = a ^ b ^ c_in;
  assign c_out = (a & b) | (b & c_in) | (a & c_in);
endmodule

projects/adder_subtractor_3bit/rtl/adder_subtractor_3bit.v
`timescale 1ns / 1ps

module adder_subtractor_3bit #(
    parameter integer N = 3
) (
    input  [N-1:0] a,
    input  [N-1:0] b,
    input          mode,
    output         c_out,
    output [  N:0] sum     // 최종 4비트 결과
);

  wire [N:0] carry;
  assign carry[0] = mode;  // 뺄셈 시 +1 역할(1의 보수 -> 2의 보수)

  genvar i;
  generate
    for (i = 0; i < N; i = i + 1) begin : gen_adder
      wire b_in_wire = b[i] ^ mode;

      full_adder fa (
          .a(a[i]),
          .b(b_in_wire),
          .c_in(carry[i]),
          .c_out(carry[i+1]),
          .sum(sum[i])
      );
    end
  endgenerate

  // ADD에서는 carry 발생, SUB에서는 borrow 발생을 표시한다.
  assign c_out  = mode ? ~carry[N] : carry[N];
  // ADD에서는 확장 캐리 비트, SUB에서는 4비트 2의 보수 결과의 부호 비트가 된다.
  assign sum[N] = mode ? ~carry[N] : carry[N];

endmodule

projects/adder_subtractor_3bit/sim/test/test_adder_subtractor_3bit.v
`timescale 1ns / 1ps

module test_adder_subtractor_3bit;

  // 1. 파라미터 및 신호 선언
  parameter integer N = 3;
  reg [N-1:0] a, b;
  reg        mode;
  wire       c_out;
  wire [N:0] sum;

  // 2. UUT (Unit Under Test) 인스턴스화
  adder_subtractor_3bit #(
      .N(N)
  ) uut (
      .a(a),
      .b(b),
      .mode(mode),
      .c_out(c_out),
      .sum(sum)
  );

  // 3. GTKWave용 VCD 파일 생성
  initial begin
    $dumpfile("test_adder_subtractor_3bit.vcd");
    $dumpvars(0, test_adder_subtractor_3bit);
  end

  // 4. 통합 검증 루프 (전수조사 + 코너 케이스)
  integer m, i, j;
  integer result_dec;
  integer expected_dec;
  integer error_count;
  reg [N:0] expected_sum;
  reg expected_c_out;
  reg [8*24-1:0] note;
  initial begin
    error_count = 0;
    $display("=====================================================================");
    $display(" Time | Mode |  A  |  B  | Result(Bin) | C/B  | Result(Dec) | Note");
    $display("=====================================================================");
    $display(" C/B : Carry for ADD, Borrow for SUB");

    for (m = 0; m < 2; m = m + 1) begin
      mode = m;
      $display("--- Mode: %s ---", (mode ? "SUBTRACT (-)" : "ADD (+)"));
      for (i = 0; i < 8; i = i + 1) begin
        for (j = 0; j < 8; j = j + 1) begin
          a = i;
          b = j;
          #10;  // 신호 전파 대기

          // 코너 케이스 및 주요 지점 레이블링
          note = "";
          if (mode == 0 && a == 7 && b == 7) note = "<< MAX ADD (Corner)";
          else if (mode == 1 && a == 0 && b == 7) note = "<< MIN SUB (Corner)";
          else if (mode == 1 && a == 7 && b == 0) note = "<< MAX SUB (Corner)";
          else if (a == 0 && b == 0) note = "<< ZERO CASE";

          if (mode == 0) begin
            expected_sum = i + j;
            expected_c_out = expected_sum[N];
            expected_dec = expected_sum;
          end else begin
            expected_sum = i - j;
            expected_c_out = (i < j);
            expected_dec = i - j;
          end

          if (mode == 0) begin
            result_dec = sum;
          end else if (sum[N]) begin
            result_dec = sum - (1 << (N + 1));
          end else begin
            result_dec = sum;
          end

          $display("%4t |  %b   | %d | %d |    %b     |  %b   |    %d      | %s", $time, mode, a,
                   b, sum, c_out, result_dec, note);

          if ((sum !== expected_sum) || (c_out !== expected_c_out) ||
              (result_dec !== expected_dec)) begin
            error_count = error_count + 1;
            $display("ERROR: expected sum=%b, c_out=%b, dec=%0d", expected_sum, expected_c_out,
                     expected_dec);
          end
        end
      end
      $display("---------------------------------------------------------------------");
    end

    if (error_count == 0) $display("Verification Task Completed Successfully.");
    else $display("Verification failed: %0d mismatches found.", error_count);
    $finish;
  end

endmodule

projects/adder_subtractor_3bit/test_adder_subtractor_3bit.vcd
$date
	Wed Mar 25 13:41:12 2026
$end
$version
	Icarus Verilog
$end
$timescale
	1ps
$end
$scope module test_adder_subtractor_3bit $end
$var wire 4 ! sum [3:0] $end
$var wire 1 " c_out $end
$var parameter 32 # N $end
$var reg 3 $ a [2:0] $end
$var reg 3 % b [2:0] $end
$var reg 1 & expected_c_out $end
$var reg 4 ' expected_sum [3:0] $end
$var reg 1 ( mode $end
$var reg 192 ) note [191:0] $end
$var integer 32 * error_count [31:0] $end
$var integer 32 + expected_dec [31:0] $end
$var integer 32 , i [31:0] $end
$var integer 32 - j [31:0] $end
$var integer 32 . m [31:0] $end
$var integer 32 / result_dec [31:0] $end
$scope module uut $end
$var wire 3 0 a [2:0] $end
$var wire 3 1 b [2:0] $end
$var wire 1 ( mode $end
$var wire 4 2 sum [3:0] $end
$var wire 4 3 carry [3:0] $end
$var wire 1 " c_out $end
$var parameter 32 4 N $end
$scope begin gen_adder[0] $end
$var wire 1 5 b_in_wire $end
$var parameter 2 6 i $end
$scope module fa $end
$var wire 1 7 a $end
$var wire 1 5 b $end
$var wire 1 8 c_in $end
$var wire 1 9 c_out $end
$var wire 1 : sum $end
$upscope $end
$upscope $end
$scope begin gen_adder[1] $end
$var wire 1 ; b_in_wire $end
$var parameter 2 < i $end
$scope module fa $end
$var wire 1 = a $end
$var wire 1 ; b $end
$var wire 1 > c_in $end
$var wire 1 ? c_out $end
$var wire 1 @ sum $end
$upscope $end
$upscope $end
$scope begin gen_adder[2] $end
$var wire 1 A b_in_wire $end
$var parameter 3 B i $end
$scope module fa $end
$var wire 1 C a $end
$var wire 1 A b $end
$var wire 1 D c_in $end
$var wire 1 E c_out $end
$var wire 1 F sum $end
$upscope $end
$upscope $end
$upscope $end
$upscope $end
$enddefinitions $end
$comment Show the parameter values. $end
$dumpall
b10 B
b1 <
b0 6
b11 4
b11 #
$end
#0
$dumpvars
0F
0E
0D
0C
0A
0@
0?
0>
0=
0;
0:
09
08
07
05
b0 3
b0 2
b0 1
b0 0
bx /
b0 .
b0 -
b0 ,
bx +
b0 *
bx )
0(
bx '
x&
b0 %
b0 $
0"
b0 !
$end
#10000
b1 !
b1 2
1:
15
b1 %
b1 1
b1 -
b0 /
b0 +
0&
b0 '
b1111000011110000100000010110100100010101010010010011110010000001000011010000010101001101000101 )
#20000
0:
b10 !
b10 2
1@
05
1;
b10 %
b10 1
b10 -
b1 /
b1 +
b1 '
b0 )
#30000
b11 !
b11 2
1:
15
b11 %
b11 1
b11 -
b10 /
b10 +
b10 '
#40000
0:
0@
b100 !
b100 2
1F
05
0;
1A
b100 %
b100 1
b100 -
b11 /
b11 +
b11 '
#50000
b101 !
b101 2
1:
15
b101 %
b101 1
b101 -
b100 /
b100 +
b100 '
#60000
0:
b110 !
b110 2
1@
05
1;
b110 %
b110 1
b110 -
b101 /
b101 +
b101 '
#70000
b111 !
b111 2
1:
15
b111 %
b111 1
b111 -
b110 /
b110 +
b110 '
#80000
0>
0@
0F
b0 3
09
b1 !
b1 2
1:
05
0;
0A
17
b0 %
b0 1
b1 $
b1 0
b1 ,
b0 -
b111 /
b111 +
b111 '
#90000
1@
1>
b10 3
19
b10 !
b10 2
0:
15
b1 %
b1 1
b1 -
b1 /
b1 +
b1 '
#100000
0F
0>
0D
09
b0 3
0?
1:
b11 !
b11 2
1@
05
1;
b10 %
b10 1
b10 -
b10 /
b10 +
b10 '
#110000
1F
1D
1?
0@
1>
b110 3
19
b100 !
b100 2
0:
15
b11 %
b11 1
b11 -
b11 /
b11 +
b11 '
#120000
0"
0>
0D
09
0?
b0 3
0E
1:
0@
b101 !
b101 2
1F
05
0;
1A
b100 %
b100 1
b100 -
b100 /
b100 +
b100 '
#130000
1@
1>
b10 3
19
b110 !
b110 2
0:
15
b101 %
b101 1
b101 -
b101 /
b101 +
b101 '
#140000
0"
0E
1F
0>
0D
09
b0 3
0?
1:
b111 !
b111 2
1@
05
1;
b110 %
b110 1
b110 -
b110 /
b110 +
b110 '
#150000
1"
1E
0F
1D
1?
0@
1>
b1110 3
19
b1000 !
b1000 2
0:
15
b111 %
b111 1
b111 -
b111 /
b111 +
b111 '
#160000
0D
0"
0?
0E
0>
0F
b0 3
09
0:
b10 !
b10 2
1@
05
0;
0A
07
1=
b0 %
b0 1
b10 $
b10 0
b10 ,
b0 -
b1000 /
b1000 +
1&
b1000 '
#170000
b11 !
b11 2
1:
15
b1 %
b1 1
b1 -
b10 /
b10 +
0&
b10 '
#180000
1F
1D
b100 3
1?
0:
b100 !
b100 2
0@
05
1;
b10 %
b10 1
b10 -
b11 /
b11 +
b11 '
#190000
b101 !
b101 2
1:
15
b11 %
b11 1
b11 -
b100 /
b100 +
b100 '
#200000
0"
0D
0?
b0 3
0E
0:
1@
b110 !
b110 2
1F
05
0;
1A
b100 %
b100 1
b100 -
b101 /
b101 +
b101 '
#210000
b111 !
b111 2
1:
15
b101 %
b101 1
b101 -
b110 /
b110 +
b110 '
#220000
1"
1E
0F
1D
b1100 3
1?
0:
b1000 !
b1000 2
0@
05
1;
b110 %
b110 1
b110 -
b111 /
b111 +
b111 '
#230000
b1001 !
b1001 2
1:
15
b111 %
b111 1
b111 -
b1000 /
b1000 +
1&
b1000 '
#240000
0"
0D
0?
0E
0>
1@
0F
b0 3
09
b11 !
b11 2
1:
05
0;
0A
17
b0 %
b0 1
b11 $
b11 0
b11 ,
b0 -
b1001 /
b1001 +
b1001 '
#250000
1F
1D
1?
0@
1>
b110 3
19
b100 !
b100 2
0:
15
b1 %
b1 1
b1 -
b11 /
b11 +
0&
b11 '
#260000
0>
b100 3
09
1:
b101 !
b101 2
0@
05
1;
b10 %
b10 1
b10 -
b100 /
b100 +
b100 '
#270000
1@
1>
b110 3
19
b110 !
b110 2
0:
15
b11 %
b11 1
b11 -
b101 /
b101 +
b101 '
#280000
0D
0?
0"
0>
09
b0 3
0E
1:
1@
b111 !
b111 2
1F
05
0;
1A
b100 %
b100 1
b100 -
b110 /
b110 +
b110 '
#290000
1"
1E
0F
1D
1?
0@
1>
b1110 3
19
b1000 !
b1000 2
0:
15
b101 %
b101 1
b101 -
b111 /
b111 +
b111 '
#300000
0>
b1100 3
09
1:
b1001 !
b1001 2
0@
05
1;
b110 %
b110 1
b110 -
b1000 /
b1000 +
1&
b1000 '
#310000
1@
1>
b1110 3
19
b1010 !
b1010 2
0:
15
b111 %
b111 1
b111 -
b1001 /
b1001 +
b1001 '
#320000
0"
0E
0D
0?
0>
b0 3
09
0:
0@
b100 !
b100 2
1F
05
0;
0A
07
0=
1C
b0 %
b0 1
b100 $
b100 0
b100 ,
b0 -
b1010 /
b1010 +
b1010 '
#330000
b101 !
b101 2
1:
15
b1 %
b1 1
b1 -
b100 /
b100 +
0&
b100 '
#340000
0:
b110 !
b110 2
1@
05
1;
b10 %
b10 1
b10 -
b101 /
b101 +
b101 '
#350000
b111 !
b111 2
1:
15
b11 %
b11 1
b11 -
b110 /
b110 +
b110 '
#360000
1"
b1000 3
1E
0:
0@
b1000 !
b1000 2
0F
05
0;
1A
b100 %
b100 1
b100 -
b111 /
b111 +
b111 '
#370000
b1001 !
b1001 2
1:
15
b101 %
b101 1
b101 -
b1000 /
b1000 +
1&
b1000 '
#380000
0:
b1010 !
b1010 2
1@
05
1;
b110 %
b110 1
b110 -
b1001 /
b1001 +
b1001 '
#390000
b1011 !
b1011 2
1:
15
b111 %
b111 1
b111 -
b1010 /
b1010 +
b1010 '
#400000
0"
0E
0>
0@
1F
b0 3
09
b101 !
b101 2
1:
05
0;
0A
17
b0 %
b0 1
b101 $
b101 0
b101 ,
b0 -
b1011 /
b1011 +
b1011 '
#410000
1@
1>
b10 3
19
b110 !
b110 2
0:
15
b1 %
b1 1
b1 -
b101 /
b101 +
0&
b101 '
#420000
0"
0E
1F
0>
0D
09
b0 3
0?
1:
b111 !
b111 2
1@
05
1;
b10 %
b10 1
b10 -
b110 /
b110 +
b110 '
#430000
1"
1E
0F
1D
1?
0@
1>
b1110 3
19
b1000 !
b1000 2
0:
15
b11 %
b11 1
b11 -
b111 /
b111 +
b111 '
#440000
0>
0D
09
b1000 3
0?
1:
0@
b1001 !
b1001 2
0F
05
0;
1A
b100 %
b100 1
b100 -
b1000 /
b1000 +
1&
b1000 '
#450000
1@
1>
b1010 3
19
b1010 !
b1010 2
0:
15
b101 %
b101 1
b101 -
b1001 /
b1001 +
b1001 '
#460000
0F
0>
0D
09
b1000 3
0?
1:
b1011 !
b1011 2
1@
05
1;
b110 %
b110 1
b110 -
b1010 /
b1010 +
b1010 '
#470000
1F
1D
1?
0@
1>
b1110 3
19
b1100 !
b1100 2
0:
15
b111 %
b111 1
b111 -
b1011 /
b1011 +
b1011 '
#480000
0"
0E
0D
0?
0>
1F
b0 3
09
0:
b110 !
b110 2
1@
05
0;
0A
07
1=
b0 %
b0 1
b110 $
b110 0
b110 ,
b0 -
b1100 /
b1100 +
b1100 '
#490000
b111 !
b111 2
1:
15
b1 %
b1 1
b1 -
b110 /
b110 +
0&
b110 '
#500000
1"
1E
0F
1D
b1100 3
1?
0:
b1000 !
b1000 2
0@
05
1;
b10 %
b10 1
b10 -
b111 /
b111 +
b111 '
#510000
b1001 !
b1001 2
1:
15
b11 %
b11 1
b11 -
b1000 /
b1000 +
1&
b1000 '
#520000
0D
b1000 3
0?
0:
1@
b1010 !
b1010 2
0F
05
0;
1A
b100 %
b100 1
b100 -
b1001 /
b1001 +
b1001 '
#530000
b1011 !
b1011 2
1:
15
b101 %
b101 1
b101 -
b1010 /
b1010 +
b1010 '
#540000
1F
1D
b1100 3
1?
0:
b1100 !
b1100 2
0@
05
1;
b110 %
b110 1
b110 -
b1011 /
b1011 +
b1011 '
#550000
b1101 !
b1101 2
1:
15
b111 %
b111 1
b111 -
b1100 /
b1100 +
b1100 '
#560000
0"
0E
0D
0?
0>
1@
1F
b0 3
09
b111 !
b111 2
1:
05
0;
0A
17
b0 %
b0 1
b111 $
b111 0
b111 ,
b0 -
b1101 /
b1101 +
b1101 '
#570000
1"
1E
0F
1D
1?
0@
1>
b1110 3
19
b1000 !
b1000 2
0:
15
b1 %
b1 1
b1 -
b111 /
b111 +
0&
b111 '
#580000
0>
b1100 3
09
1:
b1001 !
b1001 2
0@
05
1;
b10 %
b10 1
b10 -
b1000 /
b1000 +
1&
b1000 '
#590000
1@
1>
b1110 3
19
b1010 !
b1010 2
0:
15
b11 %
b11 1
b11 -
b1001 /
b1001 +
b1001 '
#600000
0D
0?
0>
b1000 3
09
1:
1@
b1011 !
b1011 2
0F
05
0;
1A
b100 %
b100 1
b100 -
b1010 /
b1010 +
b1010 '
#610000
1F
1D
1?
0@
1>
b1110 3
19
b1100 !
b1100 2
0:
15
b101 %
b101 1
b101 -
b1011 /
b1011 +
b1011 '
#620000
0>
b1100 3
09
1:
b1101 !
b1101 2
0@
05
1;
b110 %
b110 1
b110 -
b1100 /
b1100 +
b1100 '
#630000
1@
1>
b1110 3
19
b1110 !
b1110 2
0:
15
b111 %
b111 1
b111 -
b1101 /
b1101 +
b1101 '
#640000
0F
1>
0@
1D
19
1?
1E
0:
07
0=
0C
18
0"
b0 !
b0 2
15
1;
1A
b0 %
b0 1
b0 $
b0 0
b1111 3
1(
b1 .
b0 ,
b0 -
b1110 /
b1110 +
b1110 '
b111100001111000010000001001101010000010101100000100000010000010100010001000100001000000010100001000011011011110111001001101110011001010111001000101001 )
#650000
1"
0E
1F
0D
0?
1@
0>
b1 3
09
b1111 !
b1111 2
1:
05
b1 %
b1 1
b1 -
b0 /
b0 +
0&
b0 '
b1111000011110000100000010110100100010101010010010011110010000001000011010000010101001101000101 )
#660000
1>
b11 3
19
0:
b1110 !
b1110 2
1@
15
0;
b10 %
b10 1
b10 -
b11111111111111111111111111111111 /
b11111111111111111111111111111111 +
1&
b1111 '
b0 )
#670000
0@
0>
b1 3
09
b1101 !
b1101 2
1:
05
b11 %
b11 1
b11 -
b11111111111111111111111111111110 /
b11111111111111111111111111111110 +
b1110 '
#680000
1D
1?
1>
b111 3
19
0:
0@
b1100 !
b1100 2
1F
15
1;
0A
b100 %
b100 1
b100 -
b11111111111111111111111111111101 /
b11111111111111111111111111111101 +
b1101 '
#690000
0F
0D
0?
1@
0>
b1 3
09
b1011 !
b1011 2
1:
05
b101 %
b101 1
b101 -
b11111111111111111111111111111100 /
b11111111111111111111111111111100 +
b1100 '
#700000
1>
b11 3
19
0:
b1010 !
b1010 2
1@
15
0;
b110 %
b110 1
b110 -
b11111111111111111111111111111011 /
b11111111111111111111111111111011 +
b1011 '
#710000
0@
0>
b1 3
09
b1001 !
b1001 2
1:
05
b111 %
b111 1
b111 -
b11111111111111111111111111111010 /
b11111111111111111111111111111010 +
b1010 '
#720000
0"
1E
1D
1?
0F
1>
b1 !
b1 2
1:
b1111 3
19
15
1;
1A
17
b0 %
b0 1
b1 $
b1 0
b1 ,
b0 -
b11111111111111111111111111111001 /
b11111111111111111111111111111001 +
b1001 '
b111100001111000010000001001101010010010100111000100000010100110101010101000010001000000010100001000011011011110111001001101110011001010111001000101001 )
#730000
b0 !
b0 2
0:
05
b1 %
b1 1
b1 -
b1 /
b1 +
0&
b1 '
b0 )
#740000
1"
0E
1F
0D
b11 3
0?
1:
b1111 !
b1111 2
1@
15
0;
b10 %
b10 1
b10 -
b0 /
b0 +
b0 '
#750000
b1110 !
b1110 2
0:
05
b11 %
b11 1
b11 -
b11111111111111111111111111111111 /
b11111111111111111111111111111111 +
1&
b1111 '
#760000
1D
b111 3
1?
1:
0@
b1101 !
b1101 2
1F
15
1;
0A
b100 %
b100 1
b100 -
b11111111111111111111111111111110 /
b11111111111111111111111111111110 +
b1110 '
#770000
b1100 !
b1100 2
0:
05
b101 %
b101 1
b101 -
b11111111111111111111111111111101 /
b11111111111111111111111111111101 +
b1101 '
#780000
0F
0D
b11 3
0?
1:
b1011 !
b1011 2
1@
15
0;
b110 %
b110 1
b110 -
b11111111111111111111111111111100 /
b11111111111111111111111111111100 +
b1100 '
#790000
b1010 !
b1010 2
0:
05
b111 %
b111 1
b111 -
b11111111111111111111111111111011 /
b11111111111111111111111111111011 +
b1011 '
#800000
0"
1E
1>
1D
0:
19
b10 !
b10 2
1@
b1111 3
1?
15
1;
1A
07
1=
b0 %
b0 1
b10 $
b10 0
b10 ,
b0 -
b11111111111111111111111111111010 /
b11111111111111111111111111111010 +
b1010 '
#810000
0@
0>
b1101 3
09
b1 !
b1 2
1:
05
b1 %
b1 1
b1 -
b10 /
b10 +
0&
b10 '
#820000
0"
1E
0F
1>
1D
19
b1111 3
1?
0:
b0 !
b0 2
0@
15
0;
b10 %
b10 1
b10 -
b1 /
b1 +
b1 '
#830000
1"
0E
1F
0D
0?
1@
0>
b1 3
09
b1111 !
b1111 2
1:
05
b11 %
b11 1
b11 -
b0 /
b0 +
b0 '
#840000
1>
1D
19
b111 3
1?
0:
1@
b1110 !
b1110 2
1F
15
1;
0A
b100 %
b100 1
b100 -
b11111111111111111111111111111111 /
b11111111111111111111111111111111 +
1&
b1111 '
#850000
0@
0>
b101 3
09
b1101 !
b1101 2
1:
05
b101 %
b101 1
b101 -
b11111111111111111111111111111110 /
b11111111111111111111111111111110 +
b1110 '
#860000
1F
1>
1D
19
b111 3
1?
0:
b1100 !
b1100 2
0@
15
0;
b110 %
b110 1
b110 -
b11111111111111111111111111111101 /
b11111111111111111111111111111101 +
b1101 '
#870000
0F
0D
0?
1@
0>
b1 3
09
b1011 !
b1011 2
1:
05
b111 %
b111 1
b111 -
b11111111111111111111111111111100 /
b11111111111111111111111111111100 +
b1100 '
#880000
0"
1E
1D
1?
0F
1>
b11 !
b11 2
1:
b1111 3
19
15
1;
1A
17
b0 %
b0 1
b11 $
b11 0
b11 ,
b0 -
b11111111111111111111111111111011 /
b11111111111111111111111111111011 +
b1011 '
#890000
b10 !
b10 2
0:
05
b1 %
b1 1
b1 -
b11 /
b11 +
0&
b11 '
#900000
1:
b1 !
b1 2
0@
15
0;
b10 %
b10 1
b10 -
b10 /
b10 +
b10 '
#910000
b0 !
b0 2
0:
05
b11 %
b11 1
b11 -
b1 /
b1 +
b1 '
#920000
1"
b111 3
0E
1:
1@
b1111 !
b1111 2
1F
15
1;
0A
b100 %
b100 1
b100 -
b0 /
b0 +
b0 '
#930000
b1110 !
b1110 2
0:
05
b101 %
b101 1
b101 -
b11111111111111111111111111111111 /
b11111111111111111111111111111111 +
1&
b1111 '
#940000
1:
b1101 !
b1101 2
0@
15
0;
b110 %
b110 1
b110 -
b11111111111111111111111111111110 /
b11111111111111111111111111111110 +
b1110 '
#950000
b1100 !
b1100 2
0:
05
b111 %
b111 1
b111 -
b11111111111111111111111111111101 /
b11111111111111111111111111111101 +
b1101 '
#960000
0"
1>
1D
0:
19
0@
1?
b100 !
b100 2
1F
b1111 3
1E
15
1;
1A
07
0=
1C
b0 %
b0 1
b100 $
b100 0
b100 ,
b0 -
b11111111111111111111111111111100 /
b11111111111111111111111111111100 +
b1100 '
#970000
0F
0D
0?
1@
0>
b1001 3
09
b11 !
b11 2
1:
05
b1 %
b1 1
b1 -
b100 /
b100 +
0&
b100 '
#980000
1>
b1011 3
19
0:
b10 !
b10 2
1@
15
0;
b10 %
b10 1
b10 -
b11 /
b11 +
b11 '
#990000
0@
0>
b1001 3
09
b1 !
b1 2
1:
05
b11 %
b11 1
b11 -
b10 /
b10 +
b10 '
#1000000
1D
1?
0"
1>
19
b1111 3
1E
0:
0@
b0 !
b0 2
0F
15
1;
0A
b100 %
b100 1
b100 -
b1 /
b1 +
b1 '
#1010000
1"
0E
1F
0D
0?
1@
0>
b1 3
09
b1111 !
b1111 2
1:
05
b101 %
b101 1
b101 -
b0 /
b0 +
b0 '
#1020000
1>
b11 3
19
0:
b1110 !
b1110 2
1@
15
0;
b110 %
b110 1
b110 -
b11111111111111111111111111111111 /
b11111111111111111111111111111111 +
1&
b1111 '
#1030000
0@
0>
b1 3
09
b1101 !
b1101 2
1:
05
b111 %
b111 1
b111 -
b11111111111111111111111111111110 /
b11111111111111111111111111111110 +
b1110 '
#1040000
0"
1D
1?
1E
1F
1>
b101 !
b101 2
1:
b1111 3
19
15
1;
1A
17
b0 %
b0 1
b101 $
b101 0
b101 ,
b0 -
b11111111111111111111111111111101 /
b11111111111111111111111111111101 +
b1101 '
#1050000
b100 !
b100 2
0:
05
b1 %
b1 1
b1 -
b101 /
b101 +
0&
b101 '
#1060000
0F
0D
b1011 3
0?
1:
b11 !
b11 2
1@
15
0;
b10 %
b10 1
b10 -
b100 /
b100 +
b100 '
#1070000
b10 !
b10 2
0:
05
b11 %
b11 1
b11 -
b11 /
b11 +
b11 '
#1080000
0"
1D
1?
b1111 3
1E
1:
0@
b1 !
b1 2
0F
15
1;
0A
b100 %
b100 1
b100 -
b10 /
b10 +
b10 '
#1090000
b0 !
b0 2
0:
05
b101 %
b101 1
b101 -
b1 /
b1 +
b1 '
#1100000
1"
0E
1F
0D
b11 3
0?
1:
b1111 !
b1111 2
1@
15
0;
b110 %
b110 1
b110 -
b0 /
b0 +
b0 '
#1110000
b1110 !
b1110 2
0:
05
b111 %
b111 1
b111 -
b11111111111111111111111111111111 /
b11111111111111111111111111111111 +
1&
b1111 '
#1120000
0"
1E
1>
1D
0:
19
b110 !
b110 2
1@
b1111 3
1?
15
1;
1A
07
1=
b0 %
b0 1
b110 $
b110 0
b110 ,
b0 -
b11111111111111111111111111111110 /
b11111111111111111111111111111110 +
b1110 '
#1130000
0@
0>
b1101 3
09
b101 !
b101 2
1:
05
b1 %
b1 1
b1 -
b110 /
b110 +
0&
b110 '
#1140000
1F
1>
1D
19
b1111 3
1?
0:
b100 !
b100 2
0@
15
0;
b10 %
b10 1
b10 -
b101 /
b101 +
b101 '
#1150000
0F
0D
0?
1@
0>
b1001 3
09
b11 !
b11 2
1:
05
b11 %
b11 1
b11 -
b100 /
b100 +
b100 '
#1160000
0"
1>
1D
19
1?
b1111 3
1E
0:
1@
b10 !
b10 2
0F
15
1;
0A
b100 %
b100 1
b100 -
b11 /
b11 +
b11 '
#1170000
0@
0>
b1101 3
09
b1 !
b1 2
1:
05
b101 %
b101 1
b101 -
b10 /
b10 +
b10 '
#1180000
0"
1E
0F
1>
1D
19
b1111 3
1?
0:
b0 !
b0 2
0@
15
0;
b110 %
b110 1
b110 -
b1 /
b1 +
b1 '
#1190000
1"
0E
1F
0D
0?
1@
0>
b1 3
09
b1111 !
b1111 2
1:
05
b111 %
b111 1
b111 -
b0 /
b0 +
b0 '
#1200000
0"
1D
1?
1E
1F
1>
b111 !
b111 2
1:
b1111 3
19
15
1;
1A
17
b0 %
b0 1
b111 $
b111 0
b111 ,
b0 -
b11111111111111111111111111111111 /
b11111111111111111111111111111111 +
1&
b1111 '
#1210000
b110 !
b110 2
0:
05
b1 %
b1 1
b1 -
b111 /
b111 +
0&
b111 '
b111100001111000010000001001101010000010101100000100000010100110101010101000010001000000010100001000011011011110111001001101110011001010111001000101001 )
#1220000
1:
b101 !
b101 2
0@
15
0;
b10 %
b10 1
b10 -
b110 /
b110 +
b110 '
b0 )
#1230000
b100 !
b100 2
0:
05
b11 %
b11 1
b11 -
b101 /
b101 +
b101 '
#1240000
1:
1@
b11 !
b11 2
0F
15
1;
0A
b100 %
b100 1
b100 -
b100 /
b100 +
b100 '
#1250000
b10 !
b10 2
0:
05
b101 %
b101 1
b101 -
b11 /
b11 +
b11 '
#1260000
1:
b1 !
b1 2
0@
15
0;
b110 %
b110 1
b110 -
b10 /
b10 +
b10 '
#1270000
b0 !
b0 2
0:
05
b111 %
b111 1
b111 -
b1 /
b1 +
b1 '
#1280000
b10 .
b1000 ,
b1000 -
b0 /
b0 +
b0 '
